{"code":"HML","name":"Homelands","released_at":"1995-10-01","set_type":"expansion","commons":[{"name":"Abbey Matron","collector_number":"2a","rarity":"common","mana_cost":"{2}{W}","type_line":"Creature \u2014 Human Cleric","image_uri":"https://cards.scryfall.io/normal/front/1/5/158caa84-da2e-4c4c-b24d-0c035c900e20.jpg?1562587048"},{"name":"Abbey Matron","collector_number":"2b","rarity":"common","mana_cost":"{2}{W}","type_line":"Creature \u2014 Human Cleric","image_uri":"https://cards.scryfall.io/normal/front/f/d/fd950ddc-28f4-47a5-8fc1-d6f70002fceb.jpg?1562588729"},{"name":"Aysen Bureaucrats","collector_number":"3a","rarity":"common","mana_cost":"{1}{W}","type_line":"Creature \u2014 Human Advisor","image_uri":"https://cards.scryfall.io/normal/front/9/1/91170faf-3143-4fa8-88d6-eef72e1f5459.jpg?1562587766"},{"name":"Aysen Bureaucrats","collector_number":"3b","rarity":"common","mana_cost":"{1}{W}","type_line":"Creature \u2014 Human Advisor","image_uri":"https://cards.scryfall.io/normal/front/7/c/7ca3fa70-50b3-4157-afda-fe58bf72ee16.jpg?1562587740"},{"name":"Mesa Falcon","collector_number":"10a","rarity":"common","mana_cost":"{1}{W}","type_line":"Creature \u2014 Bird","image_uri":"https://cards.scryfall.io/normal/front/7/c/7c2c7004-691b-4385-ad9b-60b93d474ebd.jpg?1562587738"},{"name":"Mesa Falcon","collector_number":"10b","rarity":"common","mana_cost":"{1}{W}","type_line":"Creature \u2014 Bird","image_uri":"https://cards.scryfall.io/normal/front/0/4/04d2f5e2-fb95-48b0-b7bf-689d45fa8970.jpg?1562587033"},{"name":"Prophecy","collector_number":"11","rarity":"common","mana_cost":"{W}","type_line":"Sorcery","image_uri":"https://cards.scryfall.io/normal/front/f/5/f514eb63-3a4e-4410-ba3d-487cf81f7063.jpg?1562588721"},{"name":"Samite Alchemist","collector_number":"13a","rarity":"common","mana_cost":"{3}{W}","type_line":"Creature \u2014 Human Cleric","image_uri":"https://cards.scryfall.io/normal/front/6/8/68224871-d4c2-4b43-9ab8-c0685588b035.jpg?1562587293"},{"name":"Samite Alchemist","collector_number":"13b","rarity":"common","mana_cost":"{3}{W}","type_line":"Creature \u2014 Human Cleric","image_uri":"https://cards.scryfall.io/normal/front/0/5/0545fc43-9c67-4ad4-b1d9-6b57b53321af.jpg?1562587034"},{"name":"Serra Bestiary","collector_number":"15","rarity":"common","mana_cost":"{W}{W}","type_line":"Enchantment \u2014 Aura","image_uri":"https://cards.scryfall.io/normal/front/a/a/aab1c8b8-9b3e-444a-a12c-bd09ec899641.jpg?1562588217"},{"name":"Serra Paladin","collector_number":"17","rarity":"common","mana_cost":"{2}{W}{W}","type_line":"Creature \u2014 Human Knight","image_uri":"https://cards.scryfall.io/normal/front/7/b/7bd25adf-4d97-4229-abdb-1c060036cfbd.jpg?1562587737"},{"name":"Trade Caravan","collector_number":"19a","rarity":"common","mana_cost":"{W}","type_line":"Creature \u2014 Human Nomad","image_uri":"https://cards.scryfall.io/normal/front/f/d/fdcc821b-8125-4585-ba44-4bf8c1873fbf.jpg?1562588730"},{"name":"Trade Caravan","collector_number":"19b","rarity":"common","mana_cost":"{W}","type_line":"Creature \u2014 Human Nomad","image_uri":"https://cards.scryfall.io/normal/front/e/6/e60ddb1e-e607-4080-849c-3e1a79052729.jpg?1562588705"},{"name":"Coral Reef","collector_number":"24","rarity":"common","mana_cost":"{U}{U}","type_line":"Enchantment","image_uri":"https://cards.scryfall.io/normal/front/4/2/42fe2280-a996-4072-b5bf-f4fd56607a51.jpg?1562587267"},{"name":"Dark Maze","collector_number":"25a","rarity":"common","mana_cost":"{4}{U}","type_line":"Creature \u2014 Wall","image_uri":"https://cards.scryfall.io/normal/front/c/2/c20a8ed9-db1e-4ce8-bfb3-92604a577df7.jpg?1562588236"},{"name":"Dark Maze","collector_number":"25b","rarity":"common","mana_cost":"{4}{U}","type_line":"Creature \u2014 Wall","image_uri":"https://cards.scryfall.io/normal/front/d/3/d3d68a76-c843-4c67-90a7-2f79295798d0.jpg?1562588251"},{"name":"Giant Albatross","collector_number":"27a","rarity":"common","mana_cost":"{1}{U}","type_line":"Creature \u2014 Bird","image_uri":"https://cards.scryfall.io/normal/front/b/c/bce05870-74d3-43f1-92d0-dc1744c0138d.jpg?1562588235"},{"name":"Giant Albatross","collector_number":"27b","rarity":"common","mana_cost":"{1}{U}","type_line":"Creature \u2014 Bird","image_uri":"https://cards.scryfall.io/normal/front/e/2/e26334fc-d8ee-4b8c-ac50-5a304fae6c60.jpg?1562588701"},{"name":"Jinx","collector_number":"29","rarity":"common","mana_cost":"{1}{U}","type_line":"Instant","image_uri":"https://cards.scryfall.io/normal/front/f/8/f81fca41-2315-4d12-b05c-d921a4c3c19e.jpg?1562588727"},{"name":"Labyrinth Minotaur","collector_number":"30a","rarity":"common","mana_cost":"{3}{U}","type_line":"Creature \u2014 Minotaur","image_uri":"https://cards.scryfall.io/normal/front/e/b/eb8c1786-a2c1-43f9-9cef-8c4542833093.jpg?1562588711"},{"name":"Labyrinth Minotaur","collector_number":"30b","rarity":"common","mana_cost":"{3}{U}","type_line":"Creature \u2014 Minotaur","image_uri":"https://cards.scryfall.io/normal/front/0/6/0663c756-9db9-4298-8a6e-a1af935286a0.jpg?1562587037"},{"name":"Memory Lapse","collector_number":"32a","rarity":"common","mana_cost":"{1}{U}","type_line":"Instant","image_uri":"https://cards.scryfall.io/normal/front/3/d/3d2cc591-3a81-468a-91a4-3c3aac83a21a.jpg?1562587259"},{"name":"Memory Lapse","collector_number":"32b","rarity":"common","mana_cost":"{1}{U}","type_line":"Instant","image_uri":"https://cards.scryfall.io/normal/front/6/c/6c8b5df3-6153-470e-be9c-f38d3cf66081.jpg?1562587296"},{"name":"Merchant Scroll","collector_number":"33","rarity":"common","mana_cost":"{1}{U}","type_line":"Sorcery","image_uri":"https://cards.scryfall.io/normal/front/d/4/d4133ceb-6176-411a-9eb8-51721c1bb435.jpg?1732047632"},{"name":"Reef Pirates","collector_number":"36a","rarity":"common","mana_cost":"{1}{U}{U}","type_line":"Creature \u2014 Zombie Pirate","image_uri":"https://cards.scryfall.io/normal/front/5/b/5b742d75-860d-4b90-89cb-4292f18aed39.jpg?1562587290"},{"name":"Reef Pirates","collector_number":"36b","rarity":"common","mana_cost":"{1}{U}{U}","type_line":"Creature \u2014 Zombie Pirate","image_uri":"https://cards.scryfall.io/normal/front/b/7/b7c5e641-0276-4321-b486-ef8602a5f185.jpg?1562588230"},{"name":"Cemetery Gate","collector_number":"44a","rarity":"common","mana_cost":"{2}{B}","type_line":"Creature \u2014 Wall","image_uri":"https://cards.scryfall.io/normal/front/0/c/0c6f0614-06dc-4bd2-b8b9-d951ae27db21.jpg?1575874678"},{"name":"Cemetery Gate","collector_number":"44b","rarity":"common","mana_cost":"{2}{B}","type_line":"Creature \u2014 Wall","image_uri":"https://cards.scryfall.io/normal/front/4/a/4a7b2cc1-cb0b-4cb8-963f-453a1d5b0e3c.jpg?1562587268"},{"name":"Dry Spell","collector_number":"46a","rarity":"common","mana_cost":"{1}{B}","type_line":"Sorcery","image_uri":"https://cards.scryfall.io/normal/front/5/4/547c10ea-8ace-4496-8b99-61863c0cec1b.jpg?1562587287"},{"name":"Dry Spell","collector_number":"46b","rarity":"common","mana_cost":"{1}{B}","type_line":"Sorcery","image_uri":"https://cards.scryfall.io/normal/front/9/9/997ea663-40a1-49b7-80f1-2e1febc1b6fa.jpg?1562587769"},{"name":"Feast of the Unicorn","collector_number":"47a","rarity":"common","mana_cost":"{3}{B}","type_line":"Enchantment \u2014 Aura","image_uri":"https://cards.scryfall.io/normal/front/0/9/096e41d6-79c3-463f-ae63-872c3d8729a7.jpg?1587856900"},{"name":"Feast of the Unicorn","collector_number":"47b","rarity":"common","mana_cost":"{3}{B}","type_line":"Enchantment \u2014 Aura","image_uri":"https://cards.scryfall.io/normal/front/f/0/f05a2735-0f0d-46b5-9c2e-6c0ed8d8944d.jpg?1587856905"},{"name":"Funeral March","collector_number":"48","rarity":"common","mana_cost":"{1}{B}{B}","type_line":"Enchantment \u2014 Aura","image_uri":"https://cards.scryfall.io/normal/front/0/5/054c5678-63d1-45d9-bd51-43100fd10afd.jpg?1562587036"},{"name":"Greater Werewolf","collector_number":"51","rarity":"common","mana_cost":"{4}{B}","type_line":"Creature \u2014 Werewolf","image_uri":"https://cards.scryfall.io/normal/front/8/c/8c29c45f-db1a-43e3-ae42-1a72dabe7880.jpg?1562587760"},{"name":"Headstone","collector_number":"52","rarity":"common","mana_cost":"{1}{B}","type_line":"Instant","image_uri":"https://cards.scryfall.io/normal/front/2/f/2fdae7fa-1076-4ff3-b771-fc3f5d9ba89f.jpg?1562587064"},{"name":"Sengir Bats","collector_number":"57a","rarity":"common","mana_cost":"{1}{B}{B}","type_line":"Creature \u2014 Bat","image_uri":"https://cards.scryfall.io/normal/front/3/c/3c745c2c-4311-412d-a137-02bf6d106e46.jpg?1562587258"},{"name":"Sengir Bats","collector_number":"57b","rarity":"common","mana_cost":"{1}{B}{B}","type_line":"Creature \u2014 Bat","image_uri":"https://cards.scryfall.io/normal/front/2/d/2ddb981a-d9e3-4efe-a383-5c98ee3b0b84.jpg?1562587062"},{"name":"Torture","collector_number":"59a","rarity":"common","mana_cost":"{B}","type_line":"Enchantment \u2014 Aura","image_uri":"https://cards.scryfall.io/normal/front/2/c/2cb8cc6c-7e24-4629-a9ce-5f717f236c37.jpg?1562587061"},{"name":"Torture","collector_number":"59b","rarity":"common","mana_cost":"{B}","type_line":"Enchantment \u2014 Aura","image_uri":"https://cards.scryfall.io/normal/front/4/c/4c7e94a3-192f-483b-9a62-b94904ba3464.jpg?1562587272"},{"name":"Aliban's Tower","collector_number":"61a","rarity":"common","mana_cost":"{1}{R}","type_line":"Instant","image_uri":"https://cards.scryfall.io/normal/front/7/f/7f711ea8-a73a-42da-8bf7-101ba588f203.jpg?1562587743"},{"name":"Aliban's Tower","collector_number":"61b","rarity":"common","mana_cost":"{1}{R}","type_line":"Instant","image_uri":"https://cards.scryfall.io/normal/front/d/6/d66e94b9-23f6-45a8-97bd-602e3aaa6711.jpg?1562588255"},{"name":"Ambush","collector_number":"62","rarity":"common","mana_cost":"{3}{R}","type_line":"Instant","image_uri":"https://cards.scryfall.io/normal/front/b/7/b7dd8623-b64a-4b47-a69d-ed62d44596fb.jpg?1562588233"},{"name":"Ambush Party","collector_number":"63a","rarity":"common","mana_cost":"{4}{R}","type_line":"Creature \u2014 Human Rogue","image_uri":"https://cards.scryfall.io/normal/front/8/7/87e24788-cc7c-4f5d-84d8-dcb35e10626f.jpg?1562587754"},{"name":"Ambush Party","collector_number":"63b","rarity":"common","mana_cost":"{4}{R}","type_line":"Creature \u2014 Human Rogue","image_uri":"https://cards.scryfall.io/normal/front/e/a/ea200e93-e5bd-4777-b47e-e53849a89fe7.jpg?1562588709"},{"name":"Anaba Bodyguard","collector_number":"66a","rarity":"common","mana_cost":"{3}{R}","type_line":"Creature \u2014 Minotaur","image_uri":"https://cards.scryfall.io/normal/front/8/8/882e3c69-dca7-4c0a-8f8c-984250e6a867.jpg?1562587755"},{"name":"Anaba Bodyguard","collector_number":"66b","rarity":"common","mana_cost":"{3}{R}","type_line":"Creature \u2014 Minotaur","image_uri":"https://cards.scryfall.io/normal/front/5/6/56a54048-4640-499b-a1c3-192917c25169.jpg?1562587288"},{"name":"Anaba Shaman","collector_number":"67a","rarity":"common","mana_cost":"{3}{R}","type_line":"Creature \u2014 Minotaur Shaman","image_uri":"https://cards.scryfall.io/normal/front/c/5/c55d086a-d848-43bc-8c1e-de96d10877e1.jpg?1575874660"},{"name":"Anaba Shaman","collector_number":"67b","rarity":"common","mana_cost":"{3}{R}","type_line":"Creature \u2014 Minotaur Shaman","image_uri":"https://cards.scryfall.io/normal/front/4/b/4b456355-9f73-45c2-9554-6e6b20d949a1.jpg?1562587271"},{"name":"Chandler","collector_number":"69","rarity":"common","mana_cost":"{4}{R}","type_line":"Legendary Creature \u2014 Human Rogue","image_uri":"https://cards.scryfall.io/normal/front/4/d/4dd3a8e3-9a90-44f4-996c-57242d3c47a5.jpg?1562587277"},{"name":"Dwarven Trader","collector_number":"72a","rarity":"common","mana_cost":"{R}","type_line":"Creature \u2014 Dwarf","image_uri":"https://cards.scryfall.io/normal/front/4/d/4db9aa47-f42b-41e9-948c-8b012c3809fb.jpg?1562587275"},{"name":"Dwarven Trader","collector_number":"72b","rarity":"common","mana_cost":"{R}","type_line":"Creature \u2014 Dwarf","image_uri":"https://cards.scryfall.io/normal/front/8/e/8e6d9318-30d6-473f-b576-cc249454440f.jpg?1562587762"},{"name":"Joven","collector_number":"77","rarity":"common","mana_cost":"{3}{R}{R}","type_line":"Legendary Creature \u2014 Human Rogue","image_uri":"https://cards.scryfall.io/normal/front/0/d/0dabe3af-cd5b-461e-95a4-aad046646419.jpg?1562587046"},{"name":"Carapace","collector_number":"84a","rarity":"common","mana_cost":"{G}","type_line":"Enchantment \u2014 Aura","image_uri":"https://cards.scryfall.io/normal/front/0/7/07159586-270e-4a3e-9b21-0d74cf3e49d7.jpg?1562587039"},{"name":"Carapace","collector_number":"84b","rarity":"common","mana_cost":"{G}","type_line":"Enchantment \u2014 Aura","image_uri":"https://cards.scryfall.io/normal/front/6/d/6d51d61e-c010-4b4e-a337-20ba5eb845e3.jpg?1562587297"},{"name":"Folk of An-Havva","collector_number":"87a","rarity":"common","mana_cost":"{G}","type_line":"Creature \u2014 Human","image_uri":"https://cards.scryfall.io/normal/front/9/f/9f4a595e-51f6-4e84-aa3a-5d9c18dc8b3f.jpg?1562587777"},{"name":"Folk of An-Havva","collector_number":"87b","rarity":"common","mana_cost":"{G}","type_line":"Creature \u2014 Human","image_uri":"https://cards.scryfall.io/normal/front/4/1/4118c563-08a7-4654-973e-ab9c454f00f9.jpg?1562587263"},{"name":"Hungry Mist","collector_number":"88a","rarity":"common","mana_cost":"{2}{G}{G}","type_line":"Creature \u2014 Elemental","image_uri":"https://cards.scryfall.io/normal/front/0/8/085973eb-56cd-4bb5-aefd-bdf36f2d2a3e.jpg?1562587040"},{"name":"Hungry Mist","collector_number":"88b","rarity":"common","mana_cost":"{2}{G}{G}","type_line":"Creature \u2014 Elemental","image_uri":"https://cards.scryfall.io/normal/front/a/4/a486eab3-3a09-4bd5-ad97-8ec620434f7e.jpg?1562588214"},{"name":"Joven's Ferrets","collector_number":"89","rarity":"common","mana_cost":"{G}","type_line":"Creature \u2014 Ferret","image_uri":"https://cards.scryfall.io/normal/front/1/f/1f95eda2-f791-46e9-bb82-31422b8c5ce4.jpg?1562587053"},{"name":"Leaping Lizard","collector_number":"90","rarity":"common","mana_cost":"{1}{G}{G}","type_line":"Creature \u2014 Lizard","image_uri":"https://cards.scryfall.io/normal/front/4/b/4b0e4744-4d73-4e6e-950b-bb4c83229499.jpg?1562587269"},{"name":"Renewal","collector_number":"93","rarity":"common","mana_cost":"{2}{G}","type_line":"Sorcery","image_uri":"https://cards.scryfall.io/normal/front/a/b/ab998cd1-2f49-42e7-b889-c6717b0ce884.jpg?1562588220"},{"name":"Shrink","collector_number":"97a","rarity":"common","mana_cost":"{G}","type_line":"Instant","image_uri":"https://cards.scryfall.io/normal/front/3/0/30785867-32f7-46c9-94c2-775078e792ae.jpg?1562587065"},{"name":"Shrink","collector_number":"97b","rarity":"common","mana_cost":"{G}","type_line":"Instant","image_uri":"https://cards.scryfall.io/normal/front/d/9/d9f4eaa1-3c2b-4f5d-8d4e-98d153899873.jpg?1562588256"},{"name":"Willow Faerie","collector_number":"99a","rarity":"common","mana_cost":"{1}{G}","type_line":"Creature \u2014 Faerie","image_uri":"https://cards.scryfall.io/normal/front/8/3/83ce80dc-86d9-4613-af98-c385ca5d1cf4.jpg?1562587749"},{"name":"Willow Faerie","collector_number":"99b","rarity":"common","mana_cost":"{1}{G}","type_line":"Creature \u2014 Faerie","image_uri":"https://cards.scryfall.io/normal/front/0/e/0e777dfe-44ed-4e73-bf77-ef4c667092d4.jpg?1709431647"},{"name":"Clockwork Gnomes","collector_number":"102","rarity":"common","mana_cost":"{4}","type_line":"Artifact Creature \u2014 Gnome","image_uri":"https://cards.scryfall.io/normal/front/3/e/3e0ca2ea-e059-4742-8ce4-22876762048c.jpg?1562587260"},{"name":"Clockwork Steed","collector_number":"103","rarity":"common","mana_cost":"{4}","type_line":"Artifact Creature \u2014 Horse","image_uri":"https://cards.scryfall.io/normal/front/9/b/9b080587-d062-42ff-abc5-8e04a20faece.jpg?1562587774"},{"name":"Clockwork Swarm","collector_number":"104","rarity":"common","mana_cost":"{4}","type_line":"Artifact Creature \u2014 Insect","image_uri":"https://cards.scryfall.io/normal/front/d/f/dfd89e5c-79dc-4a57-b5ea-16491443fea1.jpg?1562588696"},{"name":"Ebony Rhino","collector_number":"106","rarity":"common","mana_cost":"{7}","type_line":"Artifact Creature \u2014 Rhino","image_uri":"https://cards.scryfall.io/normal/front/8/1/81db749e-a1df-4615-9449-94731fa23a9f.jpg?1562587745"},{"name":"Roterothopter","collector_number":"109","rarity":"common","mana_cost":"{1}","type_line":"Artifact Creature \u2014 Thopter","image_uri":"https://cards.scryfall.io/normal/front/2/2/22148a1a-2172-4718-8ee4-08770eafed9f.jpg?1562587058"},{"name":"Serrated Arrows","collector_number":"110","rarity":"common","mana_cost":"{4}","type_line":"Artifact","image_uri":"https://cards.scryfall.io/normal/front/8/4/849a7d2b-3fdb-4e7f-b0b6-f6559dcb32e2.jpg?1562587751"}],"uncommons":[{"name":"Abbey Gargoyles","collector_number":"1","rarity":"uncommon","mana_cost":"{2}{W}{W}{W}","type_line":"Creature \u2014 Gargoyle","image_uri":"https://cards.scryfall.io/normal/front/7/1/71a5d8de-25f1-4070-a7a6-dc3f2339ce30.jpg?1562587734"},{"name":"Death Speakers","collector_number":"7","rarity":"uncommon","mana_cost":"{W}","type_line":"Creature \u2014 Human Cleric","image_uri":"https://cards.scryfall.io/normal/front/e/1/e17c19a4-0186-45a0-89b9-d7b0fb0ddd8a.jpg?1562588699"},{"name":"Rashka the Slayer","collector_number":"12","rarity":"uncommon","mana_cost":"{3}{W}{W}","type_line":"Legendary Creature \u2014 Human Archer","image_uri":"https://cards.scryfall.io/normal/front/d/d/ddf30363-9db2-44c5-8c13-dbf1aaa8c86b.jpg?1562588257"},{"name":"Serra Inquisitors","collector_number":"16","rarity":"uncommon","mana_cost":"{4}{W}","type_line":"Creature \u2014 Human Cleric","image_uri":"https://cards.scryfall.io/normal/front/f/1/f1fbe3c8-92fb-41b9-b778-726d22c63054.jpg?1562588719"},{"name":"Aether Storm","collector_number":"21","rarity":"uncommon","mana_cost":"{3}{U}","type_line":"Enchantment","image_uri":"https://cards.scryfall.io/normal/front/c/e/ce479e91-7b21-4312-a3c0-950d9f6dc029.jpg?1562588243"},{"name":"Giant Oyster","collector_number":"28","rarity":"uncommon","mana_cost":"{2}{U}{U}","type_line":"Creature \u2014 Oyster","image_uri":"https://cards.scryfall.io/normal/front/f/8/f8045d23-e6e6-474c-a3e7-ddfc6121657a.jpg?1562588722"},{"name":"Sea Sprite","collector_number":"38","rarity":"uncommon","mana_cost":"{1}{U}","type_line":"Creature \u2014 Faerie","image_uri":"https://cards.scryfall.io/normal/front/8/8/88fb001b-3afb-44f5-ab78-af2bf9a4e63a.jpg?1562587758"},{"name":"Sea Troll","collector_number":"39","rarity":"uncommon","mana_cost":"{2}{U}","type_line":"Creature \u2014 Troll","image_uri":"https://cards.scryfall.io/normal/front/b/7/b7da23d4-f9fb-40a5-8395-51b47a064600.jpg?1562588231"},{"name":"Drudge Spell","collector_number":"45","rarity":"uncommon","mana_cost":"{B}{B}","type_line":"Enchantment","image_uri":"https://cards.scryfall.io/normal/front/5/2/52b352de-e989-4ad5-963c-818092fc9f1a.jpg?1562587283"},{"name":"Ghost Hounds","collector_number":"49","rarity":"uncommon","mana_cost":"{1}{B}","type_line":"Creature \u2014 Dog Spirit","image_uri":"https://cards.scryfall.io/normal/front/d/1/d1298b43-0b10-4b7c-9d33-786d4d7bd80e.jpg?1562588248"},{"name":"Ihsan's Shade","collector_number":"53","rarity":"uncommon","mana_cost":"{3}{B}{B}{B}","type_line":"Legendary Creature \u2014 Shade Knight","image_uri":"https://cards.scryfall.io/normal/front/8/2/82351724-2814-4d9e-b065-bb72c761b2e7.jpg?1562587746"},{"name":"Irini Sengir","collector_number":"54","rarity":"uncommon","mana_cost":"{2}{B}{B}","type_line":"Legendary Creature \u2014 Vampire Dwarf","image_uri":"https://cards.scryfall.io/normal/front/5/1/518e3b77-d482-4b90-94c0-0b8cdd949b9f.jpg?1562587280"},{"name":"Sengir Autocrat","collector_number":"56","rarity":"uncommon","mana_cost":"{3}{B}","type_line":"Creature \u2014 Human","image_uri":"https://cards.scryfall.io/normal/front/0/d/0d16e024-7865-43d0-8cd8-8933ef741d05.jpg?1670457421"},{"name":"Eron the Relentless","collector_number":"73","rarity":"uncommon","mana_cost":"{3}{R}{R}","type_line":"Legendary Creature \u2014 Human Rogue","image_uri":"https://cards.scryfall.io/normal/front/b/6/b6329bd9-1e03-43e6-b50b-8abe1356ffcc.jpg?1562588227"},{"name":"Evaporate","collector_number":"74","rarity":"uncommon","mana_cost":"{2}{R}","type_line":"Sorcery","image_uri":"https://cards.scryfall.io/normal/front/a/3/a3c99939-4854-4e28-a142-4cb7f89fe898.jpg?1562587778"},{"name":"Orcish Mine","collector_number":"78","rarity":"uncommon","mana_cost":"{1}{R}{R}","type_line":"Enchantment \u2014 Aura","image_uri":"https://cards.scryfall.io/normal/front/3/a/3a630875-b43d-4591-992c-117e1212fa34.jpg?1562587256"},{"name":"Retribution","collector_number":"79","rarity":"uncommon","mana_cost":"{2}{R}{R}","type_line":"Sorcery","image_uri":"https://cards.scryfall.io/normal/front/b/3/b3adf9a6-7137-4995-9a83-2d410cb3cd20.jpg?1562588226"},{"name":"An-Havva Inn","collector_number":"82","rarity":"uncommon","mana_cost":"{1}{G}{G}","type_line":"Sorcery","image_uri":"https://cards.scryfall.io/normal/front/e/f/eff4531f-d19d-44af-861a-33087197d21c.jpg?1562588715"},{"name":"Root Spider","collector_number":"94","rarity":"uncommon","mana_cost":"{3}{G}","type_line":"Creature \u2014 Spider","image_uri":"https://cards.scryfall.io/normal/front/4/0/407d67b0-d496-401b-8844-8e3ea2fd2046.jpg?1562587262"},{"name":"Roots","collector_number":"95","rarity":"uncommon","mana_cost":"{3}{G}","type_line":"Enchantment \u2014 Aura","image_uri":"https://cards.scryfall.io/normal/front/e/f/efb4c256-e790-41ec-a9ab-e6358e810798.jpg?1562588713"},{"name":"Spectral Bears","collector_number":"98","rarity":"uncommon","mana_cost":"{1}{G}","type_line":"Creature \u2014 Bear Spirit","image_uri":"https://cards.scryfall.io/normal/front/7/e/7e13875f-f745-4afd-a830-33df9576dce8.jpg?1758622694"},{"name":"Joven's Tools","collector_number":"108","rarity":"uncommon","mana_cost":"{6}","type_line":"Artifact","image_uri":"https://cards.scryfall.io/normal/front/d/2/d2520b38-76c1-45a2-9cda-a305f70762bd.jpg?1562588249"},{"name":"An-Havva Township","collector_number":"111","rarity":"uncommon","mana_cost":"","type_line":"Land","image_uri":"https://cards.scryfall.io/normal/front/9/a/9afac347-4316-43e2-848b-e474ed563af6.jpg?1562587772"},{"name":"Aysen Abbey","collector_number":"112","rarity":"uncommon","mana_cost":"","type_line":"Land","image_uri":"https://cards.scryfall.io/normal/front/2/a/2a2e669b-61b2-4729-b636-094796fb1d93.jpg?1562587059"},{"name":"Castle Sengir","collector_number":"113","rarity":"uncommon","mana_cost":"","type_line":"Land","image_uri":"https://cards.scryfall.io/normal/front/1/6/16bfba30-4075-4bd6-9e4b-3a37641d43ce.jpg?1562587050"},{"name":"Koskun Keep","collector_number":"114","rarity":"uncommon","mana_cost":"","type_line":"Land","image_uri":"https://cards.scryfall.io/normal/front/3/9/395fe900-ed19-438e-a658-ed7cf85818e5.jpg?1562587255"},{"name":"Wizards' School","collector_number":"115","rarity":"uncommon","mana_cost":"","type_line":"Land","image_uri":"https://cards.scryfall.io/normal/front/c/d/cd736532-8e98-4f4a-b48f-a66c57efcbfd.jpg?1562588242"}],"rares":[{"name":"Aysen Crusader","collector_number":"4","rarity":"rare","mana_cost":"{2}{W}{W}","type_line":"Creature \u2014 Human Knight","image_uri":"https://cards.scryfall.io/normal/front/7/9/7908cfdc-5ed6-48a8-a5b9-351864f8b4fd.jpg?1749634351"},{"name":"Aysen Highway","collector_number":"5","rarity":"rare","mana_cost":"{3}{W}{W}{W}","type_line":"Enchantment","image_uri":"https://cards.scryfall.io/normal/front/a/d/adfa87eb-9a11-459c-bff8-87bb09b61b87.jpg?1562588221"},{"name":"Beast Walkers","collector_number":"6","rarity":"rare","mana_cost":"{1}{W}{W}","type_line":"Creature \u2014 Human Beast Soldier","image_uri":"https://cards.scryfall.io/normal/front/9/9/99b42f6c-5c7e-4ba8-b0fb-ac8564aaf825.jpg?1562587770"},{"name":"Hazduhr the Abbot","collector_number":"8","rarity":"rare","mana_cost":"{3}{W}{W}","type_line":"Legendary Creature \u2014 Human Cleric","image_uri":"https://cards.scryfall.io/normal/front/a/d/adfd416a-dddf-40e4-acf0-84057edb7a58.jpg?1562588223"},{"name":"Leeches","collector_number":"9","rarity":"rare","mana_cost":"{1}{W}{W}","type_line":"Sorcery","image_uri":"https://cards.scryfall.io/normal/front/9/0/90db206e-b254-476c-b2f3-1cd56bb5297d.jpg?1562587765"},{"name":"Serra Aviary","collector_number":"14","rarity":"rare","mana_cost":"{3}{W}","type_line":"World Enchantment","image_uri":"https://cards.scryfall.io/normal/front/6/8/688a8de2-0167-4b35-a38d-3574034a892c.jpg?1562587294"},{"name":"Soraya the Falconer","collector_number":"18","rarity":"rare","mana_cost":"{1}{W}{W}","type_line":"Legendary Creature \u2014 Human","image_uri":"https://cards.scryfall.io/normal/front/1/9/19fb3ce2-a660-4829-9af4-330cfd612f06.jpg?1562587051"},{"name":"Truce","collector_number":"20","rarity":"rare","mana_cost":"{2}{W}","type_line":"Instant","image_uri":"https://cards.scryfall.io/normal/front/3/5/35c5fd74-bd46-4833-ae25-1a11a8c15ed2.jpg?1562587068"},{"name":"Baki's Curse","collector_number":"22","rarity":"rare","mana_cost":"{2}{U}{U}","type_line":"Sorcery","image_uri":"https://cards.scryfall.io/normal/front/e/3/e3261b4c-7963-4ca0-875d-77b7c8571b3f.jpg?1562588703"},{"name":"Chain Stasis","collector_number":"23","rarity":"rare","mana_cost":"{U}","type_line":"Instant","image_uri":"https://cards.scryfall.io/normal/front/f/1/f14f0c52-67c2-4302-82bd-fbb4e3c6d4f4.jpg?1589832227"},{"name":"Forget","collector_number":"26","rarity":"rare","mana_cost":"{U}{U}","type_line":"Sorcery","image_uri":"https://cards.scryfall.io/normal/front/d/f/df3115a9-ad65-4213-9320-6f39c11676f3.jpg?1562588695"},{"name":"Marjhan","collector_number":"31","rarity":"rare","mana_cost":"{5}{U}{U}","type_line":"Creature \u2014 Serpent","image_uri":"https://cards.scryfall.io/normal/front/b/6/b6aa3299-3b7a-4ea5-bc1f-beead26d8116.jpg?1562588228"},{"name":"Mystic Decree","collector_number":"34","rarity":"rare","mana_cost":"{2}{U}{U}","type_line":"World Enchantment","image_uri":"https://cards.scryfall.io/normal/front/8/b/8b069e6a-2c0e-4fc9-8e19-08bf1245a6c0.jpg?1562587759"},{"name":"Narwhal","collector_number":"35","rarity":"rare","mana_cost":"{2}{U}{U}","type_line":"Creature \u2014 Whale","image_uri":"https://cards.scryfall.io/normal/front/2/0/202d3ed5-f493-43b6-bf36-81ad289e6fb0.jpg?1562587054"},{"name":"Reveka, Wizard Savant","collector_number":"37","rarity":"rare","mana_cost":"{2}{U}{U}","type_line":"Legendary Creature \u2014 Dwarf Wizard","image_uri":"https://cards.scryfall.io/normal/front/a/9/a952236e-3085-4e6e-8639-355976b7c8f5.jpg?1562588215"},{"name":"Wall of Kelp","collector_number":"40","rarity":"rare","mana_cost":"{U}{U}","type_line":"Creature \u2014 Plant Wall","image_uri":"https://cards.scryfall.io/normal/front/5/2/52ff5051-e24b-4453-aaae-ed4f2bf213ab.jpg?1562587284"},{"name":"Baron Sengir","collector_number":"41","rarity":"rare","mana_cost":"{5}{B}{B}{B}","type_line":"Legendary Creature \u2014 Vampire Noble","image_uri":"https://cards.scryfall.io/normal/front/5/1/51bdddac-02fc-493a-a0ea-689273252d7e.jpg?1562587281"},{"name":"Black Carriage","collector_number":"42","rarity":"rare","mana_cost":"{3}{B}{B}","type_line":"Creature \u2014 Horse","image_uri":"https://cards.scryfall.io/normal/front/8/7/87068116-6000-44ee-b47f-f5cb8c233bb2.jpg?1562587752"},{"name":"Broken Visage","collector_number":"43","rarity":"rare","mana_cost":"{4}{B}","type_line":"Instant","image_uri":"https://cards.scryfall.io/normal/front/9/b/9be199e7-feaa-4f23-b93c-3eab54a02e74.jpg?1562587775"},{"name":"Grandmother Sengir","collector_number":"50","rarity":"rare","mana_cost":"{4}{B}","type_line":"Legendary Creature \u2014 Human Wizard","image_uri":"https://cards.scryfall.io/normal/front/e/f/efb0ac91-5e8e-47b1-aa34-902eef60349f.jpg?1562588712"},{"name":"Koskun Falls","collector_number":"55","rarity":"rare","mana_cost":"{2}{B}{B}","type_line":"World Enchantment","image_uri":"https://cards.scryfall.io/normal/front/0/4/04292a4e-8910-4911-a76d-4f2c3e15da33.jpg?1562587031"},{"name":"Timmerian Fiends","collector_number":"58","rarity":"rare","mana_cost":"{1}{B}{B}","type_line":"Creature \u2014 Horror","image_uri":"https://cards.scryfall.io/normal/front/9/0/90643766-c92f-4a25-bd02-227f3c91f391.jpg?1562587763"},{"name":"Veldrane of Sengir","collector_number":"60","rarity":"rare","mana_cost":"{5}{B}{B}","type_line":"Legendary Creature \u2014 Human Rogue","image_uri":"https://cards.scryfall.io/normal/front/f/e/fe0ce7d7-d370-4ef8-b1fa-aa70b2fd5ab1.jpg?1562588732"},{"name":"An-Zerrin Ruins","collector_number":"64","rarity":"rare","mana_cost":"{2}{R}{R}","type_line":"Enchantment","image_uri":"https://cards.scryfall.io/normal/front/4/f/4f905d57-2f52-4179-8041-2667b1fb1baa.jpg?1562587278"},{"name":"Anaba Ancestor","collector_number":"65","rarity":"rare","mana_cost":"{1}{R}","type_line":"Creature \u2014 Minotaur Spirit","image_uri":"https://cards.scryfall.io/normal/front/c/4/c4d33cc0-525d-4e25-927b-b6b18087c27b.jpg?1562588238"},{"name":"Anaba Spirit Crafter","collector_number":"68","rarity":"rare","mana_cost":"{2}{R}{R}","type_line":"Creature \u2014 Minotaur Shaman","image_uri":"https://cards.scryfall.io/normal/front/e/9/e9aaabc2-1dab-4f9c-8ed3-60bc1aa995ba.jpg?1587856909"},{"name":"Dwarven Pony","collector_number":"70","rarity":"rare","mana_cost":"{R}","type_line":"Creature \u2014 Horse","image_uri":"https://cards.scryfall.io/normal/front/5/3/53a3019f-0b27-4ba3-be4c-73ed50eb9514.jpg?1562587286"},{"name":"Dwarven Sea Clan","collector_number":"71","rarity":"rare","mana_cost":"{2}{R}","type_line":"Creature \u2014 Dwarf","image_uri":"https://cards.scryfall.io/normal/front/4/c/4cb722d9-1998-4912-a6f2-4ffa8d21311a.jpg?1562587274"},{"name":"Heart Wolf","collector_number":"75","rarity":"rare","mana_cost":"{3}{R}","type_line":"Creature \u2014 Wolf","image_uri":"https://cards.scryfall.io/normal/front/e/0/e0427dcd-26da-462b-b936-a382d3d8afce.jpg?1562588698"},{"name":"Ironclaw Curse","collector_number":"76","rarity":"rare","mana_cost":"{R}","type_line":"Enchantment \u2014 Aura","image_uri":"https://cards.scryfall.io/normal/front/e/7/e796f0ff-4e7b-4849-b463-0aac860c72ea.jpg?1562588706"},{"name":"Winter Sky","collector_number":"80","rarity":"rare","mana_cost":"{R}","type_line":"Sorcery","image_uri":"https://cards.scryfall.io/normal/front/a/f/af1035f3-3027-4a41-834c-55222b13c2bc.jpg?1562588224"},{"name":"An-Havva Constable","collector_number":"81","rarity":"rare","mana_cost":"{1}{G}{G}","type_line":"Creature \u2014 Human","image_uri":"https://cards.scryfall.io/normal/front/4/2/42c5a793-a777-44f9-a977-d16d26d3f852.jpg?1562587265"},{"name":"Autumn Willow","collector_number":"83","rarity":"rare","mana_cost":"{4}{G}{G}","type_line":"Legendary Creature \u2014 Avatar","image_uri":"https://cards.scryfall.io/normal/front/c/e/cea60340-bbdb-48e2-94a6-5ac1197e978a.jpg?1562588245"},{"name":"Daughter of Autumn","collector_number":"85","rarity":"rare","mana_cost":"{2}{G}{G}","type_line":"Legendary Creature \u2014 Avatar","image_uri":"https://cards.scryfall.io/normal/front/9/7/972e9c59-f340-414c-b55b-39d46dd97e8e.jpg?1562587767"},{"name":"Faerie Noble","collector_number":"86","rarity":"rare","mana_cost":"{2}{G}","type_line":"Creature \u2014 Faerie Noble","image_uri":"https://cards.scryfall.io/normal/front/0/0/00f8931e-6402-483c-a9e8-63ee344c36a7.jpg?1562587028"},{"name":"Mammoth Harness","collector_number":"91","rarity":"rare","mana_cost":"{3}{G}","type_line":"Enchantment \u2014 Aura","image_uri":"https://cards.scryfall.io/normal/front/5/b/5be67121-068c-4770-bc42-c081577a442c.jpg?1562587292"},{"name":"Primal Order","collector_number":"92","rarity":"rare","mana_cost":"{2}{G}{G}","type_line":"Enchantment","image_uri":"https://cards.scryfall.io/normal/front/2/1/21a3b8f7-c794-40ef-9ebd-dec5357260d4.jpg?1562587056"},{"name":"Rysorian Badger","collector_number":"96","rarity":"rare","mana_cost":"{2}{G}","type_line":"Creature \u2014 Badger","image_uri":"https://cards.scryfall.io/normal/front/a/b/ab87a387-678b-4913-a0c7-85f0238cee26.jpg?1562588218"},{"name":"Willow Priestess","collector_number":"100","rarity":"rare","mana_cost":"{2}{G}{G}","type_line":"Creature \u2014 Faerie Druid","image_uri":"https://cards.scryfall.io/normal/front/c/6/c636a608-26d7-4154-8052-a093b11362b1.jpg?1562588241"},{"name":"Apocalypse Chime","collector_number":"101","rarity":"rare","mana_cost":"{2}","type_line":"Artifact","image_uri":"https://cards.scryfall.io/normal/front/c/e/cef20d8f-6e80-4fca-b6a7-541981f6a112.jpg?1615259919"},{"name":"Didgeridoo","collector_number":"105","rarity":"rare","mana_cost":"{1}","type_line":"Artifact","image_uri":"https://cards.scryfall.io/normal/front/8/2/828f8f68-abe2-4e39-b3e4-991dceacd5d9.jpg?1562587748"},{"name":"Feroz's Ban","collector_number":"107","rarity":"rare","mana_cost":"{6}","type_line":"Artifact","image_uri":"https://cards.scryfall.io/normal/front/0/1/01ff4430-c8f7-408a-aad2-a098d747ea62.jpg?1562587030"}],"mythics":[],"basics":[],"conspiracies":[]}